proposal/__init__.py
proposal/concurrent/__init__.py
proposal/concurrent/futures/__init__.py
proposal/concurrent/futures/scheduled/__init__.py
proposal/concurrent/futures/scheduled/delayed_queue.py
proposal/concurrent/futures/scheduled/scheduled_future.py
proposal/concurrent/futures/scheduled/scheduled_future_task.py
proposal/concurrent/futures/scheduled/scheduled_thread_pool_executor.py
tests/__init__.py
tests/test_scheduled_thread_pool_executor.py
proposal.concurrent.futures.scheduled-1.0.2.dist-info/LICENSE.txt
proposal.concurrent.futures.scheduled-1.0.2.dist-info/METADATA
proposal.concurrent.futures.scheduled-1.0.2.dist-info/WHEEL
proposal.concurrent.futures.scheduled-1.0.2.dist-info/top_level.txt
proposal.concurrent.futures.scheduled-1.0.2.dist-info/RECORD
