Metadata-Version: 2.1
Name: proposal.concurrent.futures.scheduled
Version: 1.0.2
Summary: Scheduled thread executor
Home-page: https://github.com/usalko/proposal_concurrent_futures_scheduled
Author: Ivan Usalko
Author-email: ivict@rambler.ru
License: Apache License, Version 2.0 (Apache-2.0)
Platform: UNKNOWN
Classifier: Programming Language :: Python :: 3
Classifier: License :: OSI Approved :: Apache Software License
Classifier: Operating System :: OS Independent
